pysmithchart/__init__.py
pysmithchart/axes.py
pysmithchart/constants.py
pysmithchart/formatters.py
pysmithchart/locators.py
pysmithchart/moebius_transform.py
pysmithchart/polar_transform.py
pysmithchart/utils.py
pysmithchart-0.5.0.dist-info/licenses/LICENSE.txt
pysmithchart-0.5.0.dist-info/METADATA
pysmithchart-0.5.0.dist-info/WHEEL
pysmithchart-0.5.0.dist-info/top_level.txt
pysmithchart-0.5.0.dist-info/RECORD
