Metadata-Version: 2.4
Name: pysmithchart
Version: 0.5.0
Summary: A Python library extending Matplotlib to generate Smith Charts.
Author-email: Paul Staerke <paul.staerke@gmail.com>, Scott Prahl <scott.prahl@oit.edu>
License-Expression: BSD-3-Clause
Project-URL: Homepage, https://github.com/scottprahl/pysmithchart
Project-URL: Documentation, https://pysmithchart.readthedocs.io
Project-URL: Source, https://github.com/scottprahl/pysmithchart
Project-URL: Tracker, https://github.com/scottprahl/pysmithchart/issues
Project-URL: Changelog, https://github.com/scottprahl/pysmithchart/blob/main/docs/CHANGELOG.rst
Keywords: Smith Chart,impedance,reflection,RF engineering,microwave
Classifier: Development Status :: 5 - Production/Stable
Classifier: Intended Audience :: Science/Research
Classifier: Topic :: Scientific/Engineering
Classifier: Programming Language :: Python
Classifier: Programming Language :: Python :: 3
Classifier: Programming Language :: Python :: 3.9
Classifier: Programming Language :: Python :: 3.10
Classifier: Programming Language :: Python :: 3.11
Classifier: Programming Language :: Python :: 3.12
Requires-Python: >=3.9
License-File: LICENSE.txt
Requires-Dist: matplotlib>=3.7.0
Requires-Dist: numpy>=1.20
Requires-Dist: scipy>=1.6
Provides-Extra: docs
Requires-Dist: Sphinx==8.1.3; extra == "docs"
Requires-Dist: nbsphinx==0.9.7; extra == "docs"
Requires-Dist: sphinx_automodapi; extra == "docs"
Requires-Dist: sphinx_rtd_theme; extra == "docs"
Provides-Extra: dev
Requires-Dist: pytest; extra == "dev"
Requires-Dist: imageio; extra == "dev"
Requires-Dist: requests; extra == "dev"
Requires-Dist: ruff; extra == "dev"
Requires-Dist: yamllint; extra == "dev"
Requires-Dist: rstcheck; extra == "dev"
Requires-Dist: pylint; extra == "dev"
Requires-Dist: pyroma; extra == "dev"
Requires-Dist: black[jupyter]; extra == "dev"
Requires-Dist: build; extra == "dev"
Requires-Dist: check-manifest; extra == "dev"
Requires-Dist: libarchive-c; extra == "dev"
Requires-Dist: pyyaml; extra == "dev"
Requires-Dist: setuptools; extra == "dev"
Requires-Dist: jupyterlab; extra == "dev"
Requires-Dist: nbconvert; extra == "dev"
Requires-Dist: nbformat; extra == "dev"
Provides-Extra: lite
Requires-Dist: jupyterlite-core==0.6.4; extra == "lite"
Requires-Dist: jupyterlite-pyodide-kernel==0.6.1; extra == "lite"
Dynamic: license-file
